heavyedge/__init__.py
heavyedge/_wasserstein.cp312-win32.pyd
heavyedge/_wasserstein.pyx
heavyedge/profile.py
heavyedge/segreg.py
heavyedge/wasserstein.py
heavyedge/api/__init__.py
heavyedge/api/edge.py
heavyedge/api/landmarks.py
heavyedge/api/mean.py
heavyedge/api/preprocess.py
heavyedge/api/profile.py
heavyedge/cli/__init__.py
heavyedge/cli/command.py
heavyedge/cli/parser.py
heavyedge/io/__init__.py
heavyedge/io/profile.py
heavyedge/io/raw.py
heavyedge/plugins/edge.py
heavyedge/plugins/mean.py
heavyedge/plugins/profile.py
heavyedge/samples/__init__.py
heavyedge/samples/config-mean.yml
heavyedge/samples/config-prep.yml
heavyedge/samples/recipes.py
heavyedge/samples/Type1/240710_095108_0000000077_HEAD_A_HEIGHT_OK.csv
heavyedge/samples/Type1/240710_095109_0000000079_HEAD_A_HEIGHT_OK.csv
heavyedge/samples/Type1/240710_095110_0000000082_HEAD_A_HEIGHT_OK.csv
heavyedge/samples/Type1/240710_095111_0000000085_HEAD_A_HEIGHT_OK.csv
heavyedge/samples/Type1/240710_095112_0000000087_HEAD_A_HEIGHT_OK.csv
heavyedge/samples/Type1/240710_095113_0000000090_HEAD_A_HEIGHT_OK.csv
heavyedge/samples/Type1/240710_095114_0000000093_HEAD_A_HEIGHT_OK.csv
heavyedge/samples/Type1/240710_095115_0000000095_HEAD_A_HEIGHT_OK.csv
heavyedge/samples/Type1/240710_095116_0000000098_HEAD_A_HEIGHT_OK.csv
heavyedge/samples/Type1/240710_095117_0000000100_HEAD_A_HEIGHT_OK.csv
heavyedge/samples/Type1/240710_095118_0000000103_HEAD_A_HEIGHT_OK.csv
heavyedge/samples/Type1/240710_095119_0000000106_HEAD_A_HEIGHT_OK.csv
heavyedge/samples/Type1/240710_095120_0000000108_HEAD_A_HEIGHT_OK.csv
heavyedge/samples/Type1/240710_095121_0000000111_HEAD_A_HEIGHT_OK.csv
heavyedge/samples/Type1/240710_095122_0000000114_HEAD_A_HEIGHT_OK.csv
heavyedge/samples/Type1/240710_095123_0000000116_HEAD_A_HEIGHT_OK.csv
heavyedge/samples/Type1/240710_095124_0000000119_HEAD_A_HEIGHT_OK.csv
heavyedge/samples/Type1/240710_095125_0000000122_HEAD_A_HEIGHT_OK.csv
heavyedge/samples/Type2/240710_103303_0000001267_HEAD_A_HEIGHT_OK.csv
heavyedge-1.8.0.dist-info/licenses/LICENSE
heavyedge-1.8.0.dist-info/METADATA
heavyedge-1.8.0.dist-info/WHEEL
heavyedge-1.8.0.dist-info/entry_points.txt
heavyedge-1.8.0.dist-info/top_level.txt
heavyedge-1.8.0.dist-info/RECORD
