Metadata-Version: 2.4
Name: heavyedge
Version: 1.8.0
Summary: Central package for heavy edge coating profile analysis
Author-email: Jisoo Song <jeesoo9595@snu.ac.kr>
License-Expression: MIT
Project-URL: homepage, https://pypi.python.org/pypi/heavyedge/
Project-URL: source, https://github.com/heavyedge/heavyedge
Project-URL: documentation, https://heavyedge.readthedocs.io
Classifier: Development Status :: 5 - Production/Stable
Classifier: Intended Audience :: Science/Research
Classifier: Programming Language :: Python
Classifier: Programming Language :: Python :: 3
Classifier: Programming Language :: Python :: 3.10
Classifier: Programming Language :: Python :: 3.11
Classifier: Programming Language :: Python :: 3.12
Classifier: Programming Language :: Python :: 3 :: Only
Classifier: Topic :: Scientific/Engineering
Classifier: Operating System :: OS Independent
Requires-Python: >=3.10
License-File: LICENSE
Requires-Dist: numpy
Requires-Dist: scipy
Requires-Dist: h5py
Requires-Dist: PyYAML
Provides-Extra: test
Requires-Dist: pytest; extra == "test"
Requires-Dist: tqdm; extra == "test"
Provides-Extra: doc
Requires-Dist: sphinx; extra == "doc"
Requires-Dist: numpydoc; extra == "doc"
Requires-Dist: pydata_sphinx_theme; extra == "doc"
Requires-Dist: matplotlib; extra == "doc"
Provides-Extra: dev
Requires-Dist: flake8; extra == "dev"
Requires-Dist: black; extra == "dev"
Requires-Dist: isort; extra == "dev"
Requires-Dist: heavyedge[doc,test]; extra == "dev"
Dynamic: license-file
